gradio_mapping/__init__.py
gradio_mapping/mapping.py
gradio_mapping/mapping.pyi
gradio_mapping/templates/component/index.js
gradio_mapping/templates/component/style.css
gradio_mapping/templates/example/index.js
gradio_mapping/templates/example/style.css
gradio_mapping-0.0.6.dist-info/METADATA
gradio_mapping-0.0.6.dist-info/WHEEL
gradio_mapping-0.0.6.dist-info/RECORD
